lit_diffusion/__about__.py
lit_diffusion/__init__.py
lit_diffusion/my_module.py
lightning_diffusion-0.0.0.dev0.dist-info/LICENSE
lightning_diffusion-0.0.0.dev0.dist-info/METADATA
lightning_diffusion-0.0.0.dev0.dist-info/WHEEL
lightning_diffusion-0.0.0.dev0.dist-info/top_level.txt
lightning_diffusion-0.0.0.dev0.dist-info/RECORD
