Metadata-Version: 2.1
Name: lightning-diffusion
Version: 0.0.0.dev0
Summary: PyTorch Lightning Sample project.
Home-page: https://github.com/Lightning-AI/lightning-diffusion
Download-URL: https://github.com/Lightning-AI/lightning-diffusion
Author: Lightning-AI et al.
Author-email: name@lightning.ai
License: TBD
Project-URL: Bug Tracker, https://github.com/Lightning-AI/lightning-diffusion/issues
Project-URL: Documentation, https://lightning-diffusion.rtfd.io/en/latest/
Project-URL: Source Code, https://github.com/Lightning-AI/lightning-diffusion
Keywords: deep learning,pytorch,AI
Classifier: Environment :: Console
Classifier: Natural Language :: English
Classifier: Development Status :: 3 - Alpha
Classifier: Intended Audience :: Developers
Classifier: Topic :: Scientific/Engineering :: Artificial Intelligence
Classifier: Topic :: Scientific/Engineering :: Information Analysis
Classifier: Operating System :: OS Independent
Classifier: Programming Language :: Python :: 3
Classifier: Programming Language :: Python :: 3.8
Classifier: Programming Language :: Python :: 3.9
Classifier: Programming Language :: Python :: 3.10
Requires-Python: >=3.8
License-File: LICENSE
Requires-Dist: torch (>=1.9.*)
Requires-Dist: lightning (>=1.8.1)
